piccup/__init__.py
piccup/core.py
piccup-0.1.1.dist-info/LICENSE
piccup-0.1.1.dist-info/METADATA
piccup-0.1.1.dist-info/WHEEL
piccup-0.1.1.dist-info/top_level.txt
piccup-0.1.1.dist-info/RECORD
