Metadata-Version: 2.1
Name: piccup
Version: 0.1.1
Summary: Render HTML from Python using plain data structures, inspired by Clojure's Hiccup
Home-page: https://github.com/alexjuda/piccup
Author: Alexander Juda
License: UNKNOWN
Platform: UNKNOWN
Classifier: Development Status :: 3 - Alpha
Classifier: Environment :: Web Environment
Classifier: License :: OSI Approved :: MIT License
Classifier: Programming Language :: Python :: 3
Classifier: Topic :: Text Processing :: Markup :: HTML
Requires-Python: >=3
